ilpyt/__init__.py
ilpyt/agents/__init__.py
ilpyt/agents/a2c_agent.py
ilpyt/agents/base_agent.py
ilpyt/agents/dqn_agent.py
ilpyt/agents/gail_agent.py
ilpyt/agents/gcl_agent.py
ilpyt/agents/heuristic_agent.py
ilpyt/agents/imitation_agent.py
ilpyt/agents/ppo_agent.py
ilpyt/algos/__init__.py
ilpyt/algos/apprentice.py
ilpyt/algos/base_algo.py
ilpyt/algos/bc.py
ilpyt/algos/dagger.py
ilpyt/algos/gail.py
ilpyt/algos/gcl.py
ilpyt/algos/rl.py
ilpyt/envs/__init__.py
ilpyt/envs/dummy_vec_env.py
ilpyt/envs/subproc_vec_env.py
ilpyt/envs/vec_env.py
ilpyt/nets/__init__.py
ilpyt/nets/base_net.py
ilpyt/nets/net1d.py
ilpyt/nets/net2d.py
ilpyt/runners/__init__.py
ilpyt/runners/runner.py
ilpyt/utils/__init__.py
ilpyt/utils/agent_utils.py
ilpyt/utils/env_utils.py
ilpyt/utils/net_utils.py
ilpyt/utils/replay_memory.py
ilpyt/utils/seed_utils.py
ilpyt-0.1.0.dist-info/LICENSE
ilpyt-0.1.0.dist-info/WHEEL
ilpyt-0.1.0.dist-info/METADATA
ilpyt-0.1.0.dist-info/RECORD
