Metadata-Version: 2.1
Name: ilpyt
Version: 0.1.0
Summary: The imitation learning toolbox (ilpyt) is an open-source Python code library developed at MITRE. The toolbox contains modular, optimized implementations of common deep imitation learning algorithms in PyTorch, with unified infrastructure supporting key imitation learning and reinforcement learning algorithms.
Home-page: https://github.com/mitre/ilpyt
Keywords: imitation learning,reinforcement learning,machine learning
Author: Amanda Vu
Author-email: amandavu@mitre.org
Requires-Python: >=3.8,<4.0
Classifier: Programming Language :: Python :: 3
Classifier: Programming Language :: Python :: 3.8
Classifier: Programming Language :: Python :: 3.9
Requires-Dist: Box2D (==2.3.10)
Requires-Dist: Markdown (==3.3.4)
Requires-Dist: Pillow (==7.2.0)
Requires-Dist: PyYAML (==5.3.1)
Requires-Dist: Werkzeug (==1.0.1)
Requires-Dist: absl-py (==0.11.0)
Requires-Dist: aiohttp (==3.7.4.post0)
Requires-Dist: aiohttp_cors (==0.7.0)
Requires-Dist: aioredis (==1.3.1)
Requires-Dist: async-timeout (==3.0.1)
Requires-Dist: atari-py (==0.2.5)
Requires-Dist: attrs (==19.3.0)
Requires-Dist: blessings (==1.7)
Requires-Dist: blinker (==1.4)
Requires-Dist: cachetools (==4.2.1)
Requires-Dist: certifi (==2019.11.28)
Requires-Dist: chardet (==3.0.4)
Requires-Dist: click (==7.1.2)
Requires-Dist: cloudpickle (==1.6.0)
Requires-Dist: colorama (==0.4.4)
Requires-Dist: coloredlogs (==15.0)
Requires-Dist: colorful (==0.5.4)
Requires-Dist: cryptography (==2.8)
Requires-Dist: decorator (==4.4.2)
Requires-Dist: entrypoints (==0.3)
Requires-Dist: filelock (==3.0.12)
Requires-Dist: flake8 (==3.7.9)
Requires-Dist: future (==0.18.2)
Requires-Dist: google-api-core (==1.26.1)
Requires-Dist: google-auth (==1.27.0)
Requires-Dist: google-auth-oauthlib (==0.4.2)
Requires-Dist: googleapis-common-protos (==1.53.0)
Requires-Dist: gpustat (==0.6.0)
Requires-Dist: grpcio (==1.32.0)
Requires-Dist: gym (==0.18.0)
Requires-Dist: hiredis (==1.1.0)
Requires-Dist: humanfriendly (==9.1)
Requires-Dist: idna (==2.8)
Requires-Dist: imageio (==2.9.0)
Requires-Dist: iniconfig (==1.1.1)
Requires-Dist: jsonschema (==3.2.0)
Requires-Dist: mccabe (==0.6.1)
Requires-Dist: msgpack (==1.0.2)
Requires-Dist: multidict (==5.1.0)
Requires-Dist: numpy (==1.19.5)
Requires-Dist: nvidia-ml-py3 (==7.352.0)
Requires-Dist: oauthlib (==3.1.0)
Requires-Dist: opencensus (==0.7.12)
Requires-Dist: opencensus-context (==0.1.2)
Requires-Dist: opencv-python (==4.5.1.48)
Requires-Dist: packaging (==20.9)
Requires-Dist: pandas (==1.2.3)
Requires-Dist: pluggy (==0.13.1)
Requires-Dist: prometheus-client (==0.9.0)
Requires-Dist: protobuf (==3.15.4)
Requires-Dist: psutil (==5.8.0)
Requires-Dist: py (==1.10.0)
Requires-Dist: py-spy (==0.3.5)
Requires-Dist: pyasn1 (==0.4.8)
Requires-Dist: pyasn1-modules (==0.2.8)
Requires-Dist: pycodestyle (==2.5.0)
Requires-Dist: pyflakes (==2.1.1)
Requires-Dist: pyglet (==1.5.0)
Requires-Dist: pyparsing (==2.4.7)
Requires-Dist: pyrsistent (==0.15.5)
Requires-Dist: pytest (==6.2.2)
Requires-Dist: python-dateutil (==2.8.1)
Requires-Dist: pytz (==2021.1)
Requires-Dist: ray (==1.2.0)
Requires-Dist: redis (==3.5.3)
Requires-Dist: requests (==2.22.0)
Requires-Dist: requests-oauthlib (==1.3.0)
Requires-Dist: rsa (==4.7.2)
Requires-Dist: scipy (==1.6.1)
Requires-Dist: six (==1.15.0)
Requires-Dist: tabulate (==0.8.9)
Requires-Dist: tensorboard (==2.4.1)
Requires-Dist: tensorboard-plugin-wit (==1.8.0)
Requires-Dist: toml (==0.10.2)
Requires-Dist: torch (==1.8.1)
Requires-Dist: typing-extensions (==3.7.4.3)
Requires-Dist: urllib3 (==1.25.8)
Requires-Dist: wcwidth (==0.1.8)
Requires-Dist: yarl (==1.6.3)
Project-URL: Repository, https://github.com/mitre/ilpyt
